<?xml version = '1.0' encoding = 'UTF-8'?>
<Relation class="oracle.dbtools.crest.model.design.logical.Relation" name="Pensum_Plan_FK" directorySegmentName="seg_0" id="B178FDB1-D9DA-ED78-23DA-E9233677A181">
<createdBy>totto</createdBy>
<createdTime>2021-03-29 22:06:40 UTC</createdTime>
<generatorID>5DD5D80B-5D19-4127-B957-C4B2ADC97B9E</generatorID>
<ownerDesignName>Proyecto_Fase1</ownerDesignName>
<engineerTo>
<item key="B4AECA64-FA2F-DF61-19E6-EDB5FA2C198B" value="true"/>
</engineerTo>
<sourcePk>E31A60B3-EC4C-8840-ADB3-FD25FBE375BC</sourcePk>
<identifying>true</identifying>
<optionalSource>true</optionalSource>
<optionalTarget>false</optionalTarget>
<sourceCardinality>1</sourceCardinality>
<sourceEntity>DD7A0AD4-D4DA-8524-6E46-F44A4A44857C</sourceEntity>
<targetCardinalityString>*</targetCardinalityString>
<targetEntity>8F258ECF-A5A0-0020-6864-0B55EB57F07E</targetEntity>
<transferable>true</transferable>
<deleteRule>NO ACTION</deleteRule>
</Relation>